apispec_oneofschema/__init__.py
apispec_oneofschema/plugin.py
apispec_oneofschema-3.0.2.dist-info/licenses/LICENSE.txt
apispec_oneofschema-3.0.2.dist-info/METADATA
apispec_oneofschema-3.0.2.dist-info/WHEEL
apispec_oneofschema-3.0.2.dist-info/top_level.txt
apispec_oneofschema-3.0.2.dist-info/RECORD
