Metadata-Version: 2.4
Name: apispec-oneofschema
Version: 3.0.2
Summary: Plugin for apispec providing support for Marshmallow-OneOfSchema schemas
Home-page: https://github.com/timakro/apispec-oneofschema
Author: Tim Schumacher
License: MIT
License-File: LICENSE.txt
Requires-Dist: apispec>=3.0.0
Requires-Dist: marshmallow<5.0.0
Requires-Dist: marshmallow-oneofschema
Dynamic: author
Dynamic: home-page
Dynamic: license
Dynamic: license-file
Dynamic: requires-dist
Dynamic: summary
